FluGibson/__init__.py
FluGibson/nucleotide_converter.py
FluGibson/primer_designer.py
FluGibson/plasmid_backbones/pCI.fasta
FluGibson/plasmid_backbones/pDZ-HA.fasta
FluGibson/plasmid_backbones/pDZ-M.fasta
FluGibson/plasmid_backbones/pDZ-NA.fasta
FluGibson/plasmid_backbones/pDZ-NP.fasta
FluGibson/plasmid_backbones/pDZ-NS.fasta
FluGibson/plasmid_backbones/pDZ-PA.fasta
FluGibson/plasmid_backbones/pDZ-PB1.fasta
FluGibson/plasmid_backbones/pDZ-PB2.fasta
FluGibson-1.2.dist-info/DESCRIPTION.rst
FluGibson-1.2.dist-info/METADATA
FluGibson-1.2.dist-info/metadata.json
FluGibson-1.2.dist-info/RECORD
FluGibson-1.2.dist-info/top_level.txt
FluGibson-1.2.dist-info/WHEEL
