Metadata-Version: 2.0
Name: FluGibson
Version: 1.2
Summary: A Python package for designing influenza reverse genetics                  primers using the seamless cloning methods (e.g. Gibson                  assembly, CPEC assembly).
Home-page: https://github.com/ericmjl/flu-gibson
Author: Eric J. Ma
Author-email: ericmajinglong@gmail.com
License: MIT
Keywords: biology,molecular biology,cloning
Platform: UNKNOWN
Classifier: Development Status :: 3 - Alpha
Classifier: Intended Audience :: Science/Research
Classifier: Topic :: Scientific/Engineering :: Bio-Informatics
Classifier: License :: OSI Approved :: MIT License
Classifier: Programming Language :: Python :: 3
Classifier: Programming Language :: Python :: 3.2
Classifier: Programming Language :: Python :: 3.3
Classifier: Programming Language :: Python :: 3.4
Requires: networkx
Requires: pandas
Requires: matplotlib
Requires: biopython
